airavata_django_portal_commons/__init__.py
airavata_django_portal_commons/dynamic_apps/__init__.py
airavata_django_portal_commons/dynamic_apps/context_processors.py
airavata_django_portal_commons/dynamic_apps/urls.py
airavata_django_portal_commons-1.0.3.dist-info/METADATA
airavata_django_portal_commons-1.0.3.dist-info/WHEEL
airavata_django_portal_commons-1.0.3.dist-info/top_level.txt
airavata_django_portal_commons-1.0.3.dist-info/RECORD
