Metadata-Version: 2.1
Name: airavata-django-portal-commons
Version: 1.0.3
Summary: Utilities for working with dynamically loaded Django apps.
Requires-Dist: django
Requires-Dist: importlib-metadata
